adhan/__init__.py
adhan/client.py
adhan/const.py
adhan/models.py
adhan/utils.py
adhan_time-0.3.2.dist-info/LICENSE
adhan_time-0.3.2.dist-info/METADATA
adhan_time-0.3.2.dist-info/WHEEL
adhan_time-0.3.2.dist-info/RECORD
