Metadata-Version: 2.1
Name: adhan-time
Version: 0.3.2
Summary: A complete wrapper for the aladhan API
Home-page: https://github.com/geektype/adhan.py
License: Apache-2.0
Keywords: adhan,prayer,aladhan,prayer times,islamic prayer times
Author: Abdullah Ahmed
Author-email: abdullah@softcomnetworks.com
Requires-Python: >=3.10,<4.0
Classifier: License :: OSI Approved :: Apache Software License
Classifier: Programming Language :: Python :: 3
Classifier: Programming Language :: Python :: 3.10
Classifier: Programming Language :: Python :: 3.11
Requires-Dist: requests (>=2.28.2,<3.0.0)
Project-URL: Repository, https://github.com/geektype/adhan.py
